config/__init__.py
config/load_config.py
idi_model/__init__.py
idi_model/abstracted_packages.py
idi_model/idi_monthly_model_policy_level.py
idi_model/_1_input_data_manager/__init__.py
idi_model/_1_input_data_manager/data_aggregate.py
idi_model/_1_input_data_manager/data_manipulation.py
idi_model/_1_input_data_manager/data_processing.py
idi_model/_1_input_data_manager/policy_id_diff.py
idi_model/_1_input_data_manager/projection.py
idi_model/_2_undisc_cf_projector/_1_premium_activation.py
idi_model/_2_undisc_cf_projector/_1_premium_deposit.py
idi_model/_2_undisc_cf_projector/_2_lrc_claims_deposit.py
idi_model/_2_undisc_cf_projector/_3_risk_adjustment_deposit.py
idi_model/_2_undisc_cf_projector/_4_expenses_commissions_activation.py
idi_model/_2_undisc_cf_projector/_4_expenses_commissions_deposit.py
idi_model/_2_undisc_cf_projector/_5_ceeded_cashflows_activation.py
idi_model/_2_undisc_cf_projector/_5_ceeded_cashflows_deposit.py
idi_model/_2_undisc_cf_projector/__init__.py
idi_model/_3_ifrs17_adapter/__init__.py
idi_model/_4_ifrs17_calc_engine/__init__.py
idi_model/data_merges/__init__.py
idi_model/data_merges/merge_cohort_params.py
idi_model/data_merges/monthly_loss_ration.py
idi_model/data_validator/__init__.py
idi_model/data_validator/validate_columns_df.py
idi_model/tools/__init__.py
idi_model/tools/df_tools/__init__.py
idi_model/tools/df_tools/clean_dfs_columns.py
idi_model/tools/df_tools/extract_infos.py
idi_model/tools/df_tools/sample_split.py
idi_model/workflow_process/__init__.py
idi_model/workflow_process/concat_data.py
idi_model/workflow_process/idi_workflow.py
idi_model/workflow_process/monthly_projected_at_policy_level.py
idi_model/workflow_process/quarterly_projected_at_cohort_level.py
idi_model/workflow_process/quarterly_projected_at_policy_level.py
inputs/__init__.py
almas_idi-0.0.7.dist-info/METADATA
almas_idi-0.0.7.dist-info/WHEEL
almas_idi-0.0.7.dist-info/top_level.txt
almas_idi-0.0.7.dist-info/RECORD
