Metadata-Version: 2.1
Name: almas_idi
Version: 0.0.7
Summary: idi-modules
Author: Novacture
Author-email: amine.zemni@novacture.com
Classifier: Programming Language :: Python :: 3
Requires-Dist: numpy
Requires-Dist: pandas ==2.2.2
Requires-Dist: pytest
